mocbapy/EcosystemModel.py
mocbapy/__init__.py
mocbapy/analysis.py
mocbapy/draw.py
mocbapy/test2D.py
mocbapy/test3D.py
mocbapy/utilities.py
mocbapy-0.3.dist-info/METADATA
mocbapy-0.3.dist-info/WHEEL
mocbapy-0.3.dist-info/top_level.txt
mocbapy-0.3.dist-info/RECORD
