Metadata-Version: 2.2
Name: mocbapy
Version: 0.3
Summary: Multi Objective Constraint-Based Analysis in python
Author-email: Marko Budinich <marko.budinich@gmail.com>, Anna Lambert <anna.lambert@univ-nantes.fr>
License: MIT
Project-URL: Repository, https://github.com/markobud/mocbapy
Requires-Dist: benpy
Requires-Dist: tqdm
